odoo/addons/product_information_management/LICENSE
odoo/addons/product_information_management/README.rst
odoo/addons/product_information_management/__init__.py
odoo/addons/product_information_management/__manifest__.py
odoo/addons/product_information_management/images/screen.png
odoo/addons/product_information_management/models/__init__.py
odoo/addons/product_information_management/models/product_information_attribute.py
odoo/addons/product_information_management/models/product_product.py
odoo/addons/product_information_management/models/product_template.py
odoo/addons/product_information_management/readme/CONTRIBUTORS.md
odoo/addons/product_information_management/readme/DESCRIPTION.md
odoo/addons/product_information_management/readme/USAGE.md
odoo/addons/product_information_management/security/ir.model.access.csv
odoo/addons/product_information_management/static/description/icon.png
odoo/addons/product_information_management/static/description/index.html
odoo/addons/product_information_management/views/product_information_attribute.xml
odoo/addons/product_information_management/views/product_template.xml
odoo_addon_product_information_management-18.0.1.0.0.dist-info/METADATA
odoo_addon_product_information_management-18.0.1.0.0.dist-info/WHEEL
odoo_addon_product_information_management-18.0.1.0.0.dist-info/top_level.txt
odoo_addon_product_information_management-18.0.1.0.0.dist-info/RECORD
